libsdbsdk.cpython-35m-arm-linux-gnueabihf.so
mp1ampstsdk/Makefile
mp1ampstsdk/__init__.py
mp1ampstsdk/comm_exceptions.py
mp1ampstsdk/commsdk.py
mp1ampstsdk/libsdbsdk.so
mp1ampstsdk/py_sdbsdk.py
mp1ampstsdk/sdbsdk.c
mp1ampstsdk/sdbsdk.h
mp1ampstsdk-0.0.13.dist-info/METADATA
mp1ampstsdk-0.0.13.dist-info/WHEEL
mp1ampstsdk-0.0.13.dist-info/top_level.txt
mp1ampstsdk-0.0.13.dist-info/RECORD
