Metadata-Version: 2.1
Name: mp1ampstsdk
Version: 0.0.13
Summary: MP1 OpenAMP RpMsg A7-M4 communication SDK
Home-page: https://github.com/mapellil/Mp1AmpSTSDK_Python
Author: Licio Mapelli
Author-email: licio.mapelli@st.com
License: UNKNOWN
Keywords: MP1,STM,STSDK
Platform: UNKNOWN
Classifier: Programming Language :: Python :: 3.5
Classifier: License :: OSI Approved :: MIT License
Classifier: Operating System :: POSIX :: Linux
Classifier: Development Status :: 3 - Alpha
Requires-Python: >=3.5
Requires-Dist: pyserial (>=3)
